example.py
parqet.py
parqet-1.0.4.dist-info/LICENSE
parqet-1.0.4.dist-info/METADATA
parqet-1.0.4.dist-info/WHEEL
parqet-1.0.4.dist-info/top_level.txt
parqet-1.0.4.dist-info/RECORD
