Metadata-Version: 2.1
Name: parqet
Version: 1.0.4
Summary: A simple package to interact with the Parqet API.
Author: JoghurtConnaisseur
Project-URL: Homepage, https://github.com/JoghurtConnaisseur/parqet-python/
Keywords: parqet,api,fintech,portfolio,investing,stocks
Classifier: Programming Language :: Python
Classifier: Programming Language :: Python :: 3
Requires-Python: >=3.9
License-File: LICENSE
Requires-Dist: loguru >=0.7.0
Requires-Dist: requests
